CHANGELOG.txt
LICENCE.txt
MANIFEST.in
README.txt
setup.py
starsymbolfinder/__init__.py
starsymbolfinder.egg-info/PKG-INFO
starsymbolfinder.egg-info/SOURCES.txt
starsymbolfinder.egg-info/dependency_links.txt
starsymbolfinder.egg-info/top_level.txt