Metadata-Version: 1.1
Name: starsymbolfinder
Version: 0.0.6
Summary: A package that finds a star symbol for a specified date.
Home-page: https://picstreme.com/
Author: DefaultGamingChannel
Author-email: info@picstreme.com
License: MIT
Keywords: starsymbol
Platform: UNKNOWN
Classifier: Development Status :: 4 - Beta
Classifier: Intended Audience :: Education
Classifier: Operating System :: Microsoft :: Windows :: Windows 10
Classifier: License :: OSI Approved :: MIT License
Classifier: Programming Language :: Python :: 3
